flask_dj/__init__.py
flask_dj/__project_info__.py
flask_dj/_exceptions.py
flask_dj/_utils.py
flask_dj/app_init.py
flask_dj/manage.py
flask_dj/project_creator.py
flask_dj/templates.py
flask_dj/urls.py
Flask_DJ-1.0.7.dist-info/LICENSE
Flask_DJ-1.0.7.dist-info/METADATA
Flask_DJ-1.0.7.dist-info/WHEEL
Flask_DJ-1.0.7.dist-info/entry_points.txt
Flask_DJ-1.0.7.dist-info/top_level.txt
Flask_DJ-1.0.7.dist-info/RECORD
